{
  "123": [
    {
      "category": "CATEGORY_A",
      "reason": "Оскорбление",
      "timestamp": "2025-12-06T10:03:49.117246"
    },
    {
      "category": "CATEGORY_A",
      "reason": "Оскорбление",
      "timestamp": "2025-12-06T10:03:49.118394"
    },
    {
      "category": "CATEGORY_A",
      "reason": "Оскорбление",
      "timestamp": "2025-12-06T10:03:49.119094"
    }
  ],
  "1132730997": [
    {
      "category": "CATEGORY_A",
      "reason": "прямые личные оскорбления",
      "timestamp": "2025-12-06T10:44:14.550415"
    },
    {
      "category": "CATEGORY_B",
      "reason": "Ненормативная лексика \"для выразительности\"",
      "timestamp": "2025-12-06T10:45:21.661516"
    },
    {
      "category": "CATEGORY_A",
      "reason": "экстремистские призывы",
      "timestamp": "2025-12-06T11:14:28.312309"
    },
    {
      "category": "CATEGORY_B",
      "reason": "Использование уничижительного эпитета (\"идиот\")",
      "timestamp": "2025-12-07T20:14:03.383290"
    },
    {
      "category": "CATEGORY_B",
      "reason": "Упоминание лиц, признанных иноагентами",
      "timestamp": "2025-12-07T21:56:25.701912"
    },
    {
      "category": "CATEGORY_B",
      "reason": "Упоминание лица, признанного иноагентом",
      "timestamp": "2025-12-07T21:56:34.632556"
    },
    {
      "category": "CATEGORY_B",
      "reason": "Упоминание лица, признанного иноагентом",
      "timestamp": "2025-12-07T21:57:11.115104"
    },
    {
      "category": "CATEGORY_B",
      "reason": "ненормативная лексика \"для выразительности\"",
      "timestamp": "2025-12-15T09:07:56.607956"
    },
    {
      "category": "CATEGORY_B",
      "reason": "ненормативная лексика \"для выразительности\"",
      "timestamp": "2025-12-15T09:18:33.240149"
    },
    {
      "category": "CATEGORY_B",
      "reason": "ненормативная лексика \"для выразительности\"",
      "timestamp": "2025-12-15T09:22:35.966636"
    },
    {
      "category": "CATEGORY_A",
      "reason": "прямые личные угрозы",
      "timestamp": "2025-12-15T14:15:07.396911"
    },
    {
      "category": "CATEGORY_B",
      "reason": "грубость, но не оскорбление",
      "timestamp": "2025-12-15T16:09:27.059945"
    },
    {
      "category": "CATEGORY_B",
      "reason": "ненормативная лексика \"для выразительности\"",
      "timestamp": "2025-12-15T17:44:40.098100"
    },
    {
      "category": "CATEGORY_A",
      "reason": "прямые личные оскорбления",
      "timestamp": "2025-12-16T00:56:00.870459"
    },
    {
      "category": "CATEGORY_A",
      "reason": "прямые личные оскорбления",
      "timestamp": "2025-12-16T01:12:30.880461"
    },
    {
      "category": "CATEGORY_A",
      "reason": "прямые личные оскорбления",
      "timestamp": "2025-12-16T01:12:44.426566"
    },
    {
      "category": "CATEGORY_B",
      "reason": "ненормативная лексика \"для выразительности\"",
      "timestamp": "2025-12-16T01:20:19.187040"
    },
    {
      "category": "CATEGORY_B",
      "reason": "ненормативная лексика \"для выразительности\"",
      "timestamp": "2025-12-16T01:20:43.901108"
    },
    {
      "category": "CATEGORY_A",
      "reason": "прямое личное оскорбление",
      "timestamp": "2025-12-16T01:21:18.843617"
    },
    {
      "category": "CATEGORY_B",
      "reason": "ненормативная лексика \"для выразительности\"",
      "timestamp": "2025-12-16T01:22:16.656529"
    },
    {
      "category": "CATEGORY_A",
      "reason": "прямые личные оскорбления",
      "timestamp": "2025-12-16T01:22:30.170620"
    },
    {
      "category": "CATEGORY_A",
      "reason": "прямое личное оскорбление",
      "timestamp": "2025-12-16T01:32:42.414006"
    },
    {
      "category": "CATEGORY_A",
      "reason": "прямые личные оскорбления",
      "timestamp": "2025-12-16T01:37:05.557617"
    },
    {
      "category": "CATEGORY_A",
      "reason": "прямое личное оскорбление",
      "timestamp": "2025-12-16T01:48:27.686217"
    },
    {
      "category": "CATEGORY_A",
      "reason": "прямые личные оскорбления",
      "timestamp": "2025-12-16T01:59:11.761994"
    },
    {
      "category": "CATEGORY_B",
      "reason": "ненормативная лексика \"для выразительности\"",
      "timestamp": "2025-12-16T02:15:08.480367"
    },
    {
      "category": "CATEGORY_B",
      "reason": "ненормативная лексика \"для выразительности\"",
      "timestamp": "2025-12-16T02:20:48.292304"
    },
    {
      "category": "CATEGORY_B",
      "reason": "ненормативная лексика \"для выразительности\"",
      "timestamp": "2025-12-16T02:23:06.488626"
    },
    {
      "category": "CATEGORY_A",
      "reason": "прямые личные оскорбления",
      "timestamp": "2025-12-16T02:23:12.511670"
    },
    {
      "category": "CATEGORY_B",
      "reason": "ненормативная лексика \"для выразительности\"",
      "timestamp": "2025-12-16T02:33:15.187419"
    },
    {
      "category": "CATEGORY_B",
      "reason": "ненормативная лексика \"для выразительности\"",
      "timestamp": "2025-12-16T02:33:26.973371"
    },
    {
      "category": "CATEGORY_B",
      "reason": "ненормативная лексика \"для выразительности\"",
      "timestamp": "2025-12-16T02:33:36.524591"
    },
    {
      "category": "CATEGORY_B",
      "reason": "Сообщение соответствует правилам",
      "timestamp": "2025-12-16T02:33:51.244281"
    },
    {
      "category": "CATEGORY_B",
      "reason": "ненормативная лексика и грубость для выразительности",
      "timestamp": "2025-12-16T02:34:15.563784"
    },
    {
      "category": "CATEGORY_B",
      "reason": "ненормативная лексика \"для выразительности\"",
      "timestamp": "2025-12-16T02:34:37.647998"
    },
    {
      "category": "CATEGORY_B",
      "reason": "ненормативная лексика \"для выразительности\"",
      "timestamp": "2025-12-16T02:34:47.009341"
    },
    {
      "category": "CATEGORY_A",
      "reason": "прямые личные угрозы",
      "timestamp": "2025-12-16T02:35:13.405341"
    },
    {
      "category": "CATEGORY_B",
      "reason": "ненормативная лексика \"для выразительности\"",
      "timestamp": "2025-12-16T02:35:40.161100"
    },
    {
      "category": "CATEGORY_B",
      "reason": "ненормативная лексика \"для выразительности\"",
      "timestamp": "2025-12-16T02:35:48.756095"
    },
    {
      "category": "CATEGORY_A",
      "reason": "Сообщение соответствует правилам",
      "timestamp": "2025-12-16T02:40:31.279450"
    },
    {
      "category": "CATEGORY_A",
      "reason": "Сообщение соответствует правилам",
      "timestamp": "2025-12-16T02:40:37.424062"
    },
    {
      "category": "CATEGORY_A",
      "reason": "прямые личные оскорбления",
      "timestamp": "2025-12-16T02:40:52.281768"
    },
    {
      "category": "CATEGORY_B",
      "reason": "ненормативная лексика \"для выразительности\"",
      "timestamp": "2025-12-16T02:44:10.297120"
    },
    {
      "category": "CATEGORY_A",
      "reason": "Сообщение соответствует правилам",
      "timestamp": "2025-12-16T02:57:11.804637"
    }
  ],
  "1032551771": [
    {
      "category": "CATEGORY_A",
      "reason": "использование дискриминационного термина",
      "timestamp": "2025-12-06T10:54:54.089562"
    },
    {
      "category": "CATEGORY_B",
      "reason": "Использование термина, который может быть воспринят как дискриминационный или обидный без дополнительного контекста.",
      "timestamp": "2025-12-06T10:55:00.669031"
    },
    {
      "category": "CATEGORY_A",
      "reason": "Расизм и дискриминация",
      "timestamp": "2025-12-06T10:55:13.340205"
    },
    {
      "category": "CATEGORY_A",
      "reason": "расистское выражение",
      "timestamp": "2025-12-06T10:55:24.013767"
    },
    {
      "category": "CATEGORY_A",
      "reason": "Расовая дискриминация и оскорбление",
      "timestamp": "2025-12-06T10:56:53.337177"
    },
    {
      "category": "CATEGORY_B",
      "reason": "ненормативная лексика \"для выразительности\"",
      "timestamp": "2025-12-06T10:57:21.931953"
    },
    {
      "category": "CATEGORY_B",
      "reason": "ненормативная лексика \"для выразительности\"",
      "timestamp": "2025-12-06T10:57:55.448892"
    },
    {
      "category": "CATEGORY_B",
      "reason": "Ненормативная лексика \"для выразительности\"",
      "timestamp": "2025-12-06T10:58:40.818194"
    },
    {
      "category": "CATEGORY_B",
      "reason": "ненормативная лексика \"для выразительности\"",
      "timestamp": "2025-12-06T10:59:25.996888"
    },
    {
      "category": "CATEGORY_A",
      "reason": "прямое личное оскорбление",
      "timestamp": "2025-12-06T10:59:32.367423"
    },
    {
      "category": "CATEGORY_B",
      "reason": "ненормативная лексика \"для выразительности\"",
      "timestamp": "2025-12-06T11:09:33.967762"
    },
    {
      "category": "CATEGORY_A",
      "reason": "дискриминация и разжигание ненависти",
      "timestamp": "2025-12-06T11:09:38.707544"
    },
    {
      "category": "CATEGORY_A",
      "reason": "дискриминирующее высказывание",
      "timestamp": "2025-12-06T11:09:57.713903"
    },
    {
      "category": "CATEGORY_A",
      "reason": "дискриминация",
      "timestamp": "2025-12-06T11:10:41.405690"
    },
    {
      "category": "CATEGORY_A",
      "reason": "дискриминация",
      "timestamp": "2025-12-06T11:10:46.683456"
    },
    {
      "category": "CATEGORY_A",
      "reason": "прямое личное оскорбление и дискриминация",
      "timestamp": "2025-12-06T11:14:29.248312"
    },
    {
      "category": "CATEGORY_B",
      "reason": "Расизм, дискредитация целой группы людей",
      "timestamp": "2025-12-06T11:52:44.835598"
    },
    {
      "category": "CATEGORY_B",
      "reason": "Ненормативная лексика \"для выразительности\"",
      "timestamp": "2025-12-06T11:52:45.770415"
    },
    {
      "category": "CATEGORY_A",
      "reason": "угроза",
      "timestamp": "2025-12-06T11:53:31.644760"
    },
    {
      "category": "CATEGORY_A",
      "reason": "дискриминация",
      "timestamp": "2025-12-06T11:53:38.800747"
    },
    {
      "category": "CATEGORY_A",
      "reason": "дискриминация и оскорбление определённой группы людей",
      "timestamp": "2025-12-06T11:53:52.323958"
    },
    {
      "category": "CATEGORY_B",
      "reason": "Ненормативная лексика \"для выразительности\"",
      "timestamp": "2025-12-06T11:54:06.646632"
    },
    {
      "category": "CATEGORY_A",
      "reason": "разжигание ненависти и дискриминация",
      "timestamp": "2025-12-06T11:54:18.233027"
    },
    {
      "category": "CATEGORY_A",
      "reason": "дискредитация и прямые оскорбительные высказывания по отношению к группе людей",
      "timestamp": "2025-12-06T11:54:40.163988"
    },
    {
      "category": "CATEGORY_A",
      "reason": "прямые личные оскорбления и разжигание ненависти",
      "timestamp": "2025-12-06T11:57:14.252909"
    },
    {
      "category": "CATEGORY_A",
      "reason": "Прямые личные оскорбления",
      "timestamp": "2025-12-06T11:57:45.243414"
    }
  ],
  "5274887240": [
    {
      "category": "CATEGORY_B",
      "reason": "Ненормативная лексика \"для выразительности\"",
      "timestamp": "2025-12-06T11:53:10.118112"
    },
    {
      "category": "CATEGORY_A",
      "reason": "расистское высказывание, разжигание ненависти",
      "timestamp": "2025-12-06T11:53:54.178161"
    },
    {
      "category": "CATEGORY_A",
      "reason": "разжигание ненависти",
      "timestamp": "2025-12-06T11:54:29.655071"
    },
    {
      "category": "CATEGORY_B",
      "reason": "орфографические ошибки, снижающие читаемость текста и придающие ему грубоватый оттенок. Однако серьёзных нарушений нет.",
      "timestamp": "2025-12-06T22:07:36.388056"
    }
  ],
  "1034206021": [
    {
      "category": "CATEGORY_A",
      "reason": "Сообщение соответствует правилам",
      "timestamp": "2025-12-15T14:15:08.388895"
    },
    {
      "category": "CATEGORY_A",
      "reason": "Сообщение соответствует правилам",
      "timestamp": "2025-12-15T14:15:09.077487"
    },
    {
      "category": "CATEGORY_A",
      "reason": "Сообщение соответствует правилам",
      "timestamp": "2025-12-15T14:15:09.775488"
    },
    {
      "category": "CATEGORY_B",
      "reason": "Сообщение соответствует правилам",
      "timestamp": "2025-12-15T17:14:44.479592"
    },
    {
      "category": "CATEGORY_B",
      "reason": "ненормативная лексика \"для выразительности\"",
      "timestamp": "2025-12-15T17:15:14.635253"
    },
    {
      "category": "CATEGORY_B",
      "reason": "ненормативная лексика \"для выразительности\"",
      "timestamp": "2025-12-15T17:42:11.418899"
    },
    {
      "category": "CATEGORY_A",
      "reason": "Сообщение соответствует правилам",
      "timestamp": "2025-12-15T19:14:51.992645"
    },
    {
      "category": "CATEGORY_A",
      "reason": "прямые личные оскорбления",
      "timestamp": "2025-12-15T19:17:11.150234"
    }
  ],
  "1346860696": [
    {
      "category": "CATEGORY_A",
      "reason": "Сообщение соответствует правилам",
      "timestamp": "2025-12-16T02:41:47.322862"
    },
    {
      "category": "CATEGORY_B",
      "reason": "ненормативная лексика \"для выразительности\"",
      "timestamp": "2025-12-16T02:41:54.357308"
    },
    {
      "category": "CATEGORY_B",
      "reason": "ненормативная лексика \"для выразительности\"",
      "timestamp": "2025-12-16T02:56:49.643926"
    },
    {
      "category": "CATEGORY_B",
      "reason": "ненормативная лексика \"для выразительности\"",
      "timestamp": "2025-12-16T03:06:35.822727"
    },
    {
      "category": "CATEGORY_B",
      "reason": "ненормативная лексика \"для выразительности\"",
      "timestamp": "2025-12-16T03:08:12.370710"
    }
  ]
}